odoo/addons/purchase_invoicing_no_zero_line/README.rst
odoo/addons/purchase_invoicing_no_zero_line/__init__.py
odoo/addons/purchase_invoicing_no_zero_line/__manifest__.py
odoo/addons/purchase_invoicing_no_zero_line/i18n/de.po
odoo/addons/purchase_invoicing_no_zero_line/i18n/es.po
odoo/addons/purchase_invoicing_no_zero_line/i18n/fr.po
odoo/addons/purchase_invoicing_no_zero_line/i18n/it.po
odoo/addons/purchase_invoicing_no_zero_line/i18n/purchase_invoicing_no_zero_line.pot
odoo/addons/purchase_invoicing_no_zero_line/models/__init__.py
odoo/addons/purchase_invoicing_no_zero_line/models/account_journal.py
odoo/addons/purchase_invoicing_no_zero_line/models/account_move.py
odoo/addons/purchase_invoicing_no_zero_line/readme/CONFIGURE.rst
odoo/addons/purchase_invoicing_no_zero_line/readme/CONTRIBUTORS.rst
odoo/addons/purchase_invoicing_no_zero_line/readme/DESCRIPTION.rst
odoo/addons/purchase_invoicing_no_zero_line/static/description/icon.png
odoo/addons/purchase_invoicing_no_zero_line/static/description/icon.svg
odoo/addons/purchase_invoicing_no_zero_line/static/description/index.html
odoo/addons/purchase_invoicing_no_zero_line/tests/__init__.py
odoo/addons/purchase_invoicing_no_zero_line/tests/test_purchase_invoicing_no_zero_line.py
odoo/addons/purchase_invoicing_no_zero_line/views/account_view.xml
odoo_addon_purchase_invoicing_no_zero_line-16.0.1.0.1.dist-info/METADATA
odoo_addon_purchase_invoicing_no_zero_line-16.0.1.0.1.dist-info/WHEEL
odoo_addon_purchase_invoicing_no_zero_line-16.0.1.0.1.dist-info/top_level.txt
odoo_addon_purchase_invoicing_no_zero_line-16.0.1.0.1.dist-info/RECORD
