Metadata-Version: 2.1
Name: odoo-addon-purchase_invoicing_no_zero_line
Version: 16.0.1.0.1
Summary: Avoid creation of zero quantity invoice lines from purchase
Home-page: https://github.com/OCA/account-invoicing
Author: Digital5 S.L., Odoo Community Association (OCA)
Author-email: support@odoo-community.org
License: AGPL-3
Classifier: Programming Language :: Python
Classifier: Framework :: Odoo
Classifier: Framework :: Odoo :: 16.0
Classifier: License :: OSI Approved :: GNU Affero General Public License v3
Requires-Python: >=3.10
Requires-Dist: odoo<16.1dev,>=16.0a
